gptme/__init__.py
gptme/__main__.py
gptme/__version__.py
gptme/chat.py
gptme/cli.py
gptme/codeblock.py
gptme/commands.py
gptme/config.py
gptme/constants.py
gptme/context/__init__.py
gptme/context/compress.py
gptme/context/config.py
gptme/context/selector/__init__.py
gptme/context/selector/base.py
gptme/context/selector/config.py
gptme/context/selector/file_config.py
gptme/context/selector/file_integration.py
gptme/context/selector/file_selector.py
gptme/context/selector/hybrid.py
gptme/context/selector/llm_based.py
gptme/context/selector/rule_based.py
gptme/context/task_analyzer.py
gptme/dirs.py
gptme/eval/__init__.py
gptme/eval/__main__.py
gptme/eval/agents.py
gptme/eval/cost.py
gptme/eval/dspy/README.md
gptme/eval/dspy/__init__.py
gptme/eval/dspy/__main__.py
gptme/eval/dspy/cli.py
gptme/eval/dspy/experiments.py
gptme/eval/dspy/hybrid_optimizer.py
gptme/eval/dspy/metrics.py
gptme/eval/dspy/prompt_optimizer.py
gptme/eval/dspy/reasoning_program.py
gptme/eval/dspy/signatures.py
gptme/eval/dspy/tasks.py
gptme/eval/execenv.py
gptme/eval/filestore.py
gptme/eval/main.py
gptme/eval/run.py
gptme/eval/suites/__init__.py
gptme/eval/suites/basic.py
gptme/eval/suites/browser.py
gptme/eval/suites/init_projects.py
gptme/eval/types.py
gptme/hooks/__init__.py
gptme/hooks/active_context.py
gptme/hooks/cost_awareness.py
gptme/hooks/cwd_tracking.py
gptme/hooks/form_autodetect.py
gptme/hooks/markdown_validation.py
gptme/hooks/test.py
gptme/hooks/time_awareness.py
gptme/hooks/token_awareness.py
gptme/init.py
gptme/lessons/__init__.py
gptme/lessons/auto_include.py
gptme/lessons/commands.py
gptme/lessons/hybrid_matcher.py
gptme/lessons/index.py
gptme/lessons/matcher.py
gptme/lessons/matcher_enhanced.py
gptme/lessons/parser.py
gptme/lessons/selector_config.py
gptme/lessons/selector_integration.py
gptme/lessons/skills/python-repl/SKILL.md
gptme/lessons/skills/python-repl/python_helpers.py
gptme/lessons/skills/python-repl/requirements.txt
gptme/llm/__init__.py
gptme/llm/llm_anthropic.py
gptme-0.31.0.dist-info/METADATA
gptme-0.31.0.dist-info/WHEEL
gptme-0.31.0.dist-info/entry_points.txt
gptme-0.31.0.dist-info/licenses/LICENSE
gptme-0.31.0.dist-info/RECORD
