Metadata-Version: 2.4
Name: gptme
Version: 0.31.0
Summary: Powerful AI agent for coding and general tasks. Terminal-first with shell, code execution, file editing, web browsing, vision, computer use. Unconstrained.
License-Expression: MIT
License-File: LICENSE
Author: Erik Bjäreholt
Author-email: erik@bjareho.lt
Requires-Python: >=3.10,<4.0
Classifier: Programming Language :: Python :: 3
Classifier: Programming Language :: Python :: 3.10
Classifier: Programming Language :: Python :: 3.11
Classifier: Programming Language :: Python :: 3.12
Classifier: Programming Language :: Python :: 3.13
Classifier: Programming Language :: Python :: 3.14
Provides-Extra: all
Provides-Extra: browser
Provides-Extra: computer
Provides-Extra: datascience
Provides-Extra: dspy
Provides-Extra: eval
Provides-Extra: pyinstaller
Provides-Extra: server
Provides-Extra: telemetry
Provides-Extra: tts
Provides-Extra: youtube
Requires-Dist: anthropic (>=0.47,<0.48)
Requires-Dist: bashlex (>=0.18,<0.19)
Requires-Dist: click (>=8.0,<9.0)
Requires-Dist: click-default-group (>=1.2.4,<2.0.0)
Requires-Dist: deprecated (>=1.2.18,<2.0.0)
Requires-Dist: dspy (>=3.0.2,<4.0.0) ; (python_full_version <= "3.13.0") and (extra == "dspy" or extra == "eval" or extra == "all")
Requires-Dist: flask (>=3.0,<4.0) ; extra == "server" or extra == "all"
Requires-Dist: flask-cors (>=4,<6) ; extra == "server" or extra == "all"
Requires-Dist: ipython (>=8.17.2,<9.0.0)
Requires-Dist: json-repair (>=0.32.0,<0.33.0)
Requires-Dist: lxml
Requires-Dist: matplotlib ; extra == "datascience" or extra == "all"
Requires-Dist: mcp (>=1.13.0,<2.0.0)
Requires-Dist: multiprocessing-logging (>=0.3.4,<0.4.0)
Requires-Dist: numpy ; extra == "datascience" or extra == "tts" or extra == "all" or extra == "all"
Requires-Dist: openai (>=1.0,<2.0)
Requires-Dist: opentelemetry-api (>=1.20.0,<2.0.0) ; extra == "telemetry" or extra == "all"
Requires-Dist: opentelemetry-exporter-otlp (>=1.34.1,<2.0.0) ; extra == "telemetry" or extra == "all"
Requires-Dist: opentelemetry-exporter-prometheus (>=0.55b1,<0.56) ; extra == "telemetry" or extra == "all"
Requires-Dist: opentelemetry-instrumentation-anthropic (>=0.47.3,<0.48.0) ; extra == "telemetry" or extra == "all"
Requires-Dist: opentelemetry-instrumentation-flask (>=0.55b1,<0.56) ; extra == "telemetry" or extra == "all"
Requires-Dist: opentelemetry-instrumentation-openai (>=0.47.3,<0.48.0) ; extra == "telemetry" or extra == "all"
Requires-Dist: opentelemetry-instrumentation-requests (>=0.55b1,<0.56) ; extra == "telemetry" or extra == "all"
Requires-Dist: opentelemetry-instrumentation-threading (>=0.55b1,<0.56) ; extra == "telemetry"
Requires-Dist: opentelemetry-sdk (>=1.20.0,<2.0.0) ; extra == "telemetry" or extra == "all"
Requires-Dist: pandas ; extra == "datascience" or extra == "all"
Requires-Dist: pick (>=2.2.0,<3.0.0)
Requires-Dist: pillow
Requires-Dist: platformdirs (>=4.3,<5.0)
Requires-Dist: playwright (==1.49.1) ; extra == "browser" or extra == "all"
Requires-Dist: pydantic (>=2.11.7,<3.0.0) ; extra == "server" or extra == "all"
Requires-Dist: pyinstaller (>=6.15,<7.0) ; (python_version >= "3.10" and python_version < "3.15") and (extra == "pyinstaller")
Requires-Dist: python-dateutil (>=2.9.0.post0,<3.0.0)
Requires-Dist: python-dotenv (>=1.0.0,<2.0.0)
Requires-Dist: pyyaml (>=6.0.3,<7.0.0)
Requires-Dist: questionary (>=2.1.0,<3.0.0)
Requires-Dist: rich (>=13.5.2,<14.0.0)
Requires-Dist: scipy ; extra == "tts" or extra == "all" or extra == "all"
Requires-Dist: sentence-transformers (>=5.1.2,<6.0.0) ; extra == "dspy" or extra == "eval" or extra == "all"
Requires-Dist: sounddevice (>=0.5.1,<0.6.0) ; extra == "tts" or extra == "all"
Requires-Dist: tabulate
Requires-Dist: tiktoken (>=0.7)
Requires-Dist: tomlkit
Requires-Dist: typing-extensions
Requires-Dist: youtube_transcript_api (>=0.6.1,<0.7.0) ; extra == "youtube" or extra == "all"
Project-URL: Documentation, https://gptme.org/docs/
Project-URL: Homepage, https://gptme.org/
Project-URL: Issues, https://github.com/gptme/gptme/issues
Project-URL: Repository, https://github.com/gptme/gptme
